ailine/__init__.py
ailine/main.py
ailine/.system/imports.py
ailine/.system/index.py
ailine/.system/modules/jobs.py
ailine/.system/sources/clight.json
ailine/.system/sources/logo.ico
ailine-1.0.0.dist-info/licenses/LICENSE
ailine-1.0.0.dist-info/METADATA
ailine-1.0.0.dist-info/WHEEL
ailine-1.0.0.dist-info/entry_points.txt
ailine-1.0.0.dist-info/top_level.txt
ailine-1.0.0.dist-info/RECORD
