Metadata-Version: 2.4
Name: ailine
Version: 1.0.0
Summary: AILine transforms your (Command-Line) terminal into an AI-powered (AI-Line) terminal. By using AILine, you can gain superpowers that help you manage your system and perform complex workflows in a simple way. AILine has a default action base and develops itself based on your commands.
Home-page: https://github.com/IG-onGit/AILine
Author: Irakli Gzirishvili
Author-email: gziraklirex@gmail.com
Classifier: Programming Language :: Python :: 3
Classifier: License :: OSI Approved :: MIT License
Classifier: Operating System :: OS Independent
License-File: LICENSE
Requires-Dist: clight
Dynamic: author
Dynamic: author-email
Dynamic: classifier
Dynamic: description
Dynamic: description-content-type
Dynamic: home-page
Dynamic: license-file
Dynamic: requires-dist
Dynamic: summary
